{
	"artifacts" : 
	[
		{
			"path" : "src/tactic/fd_solver/CMakeFiles/fd_solver.dir/./bounded_int2bv_solver.cpp.obj"
		},
		{
			"path" : "src/tactic/fd_solver/CMakeFiles/fd_solver.dir/./enum2bv_solver.cpp.obj"
		},
		{
			"path" : "src/tactic/fd_solver/CMakeFiles/fd_solver.dir/./fd_solver.cpp.obj"
		},
		{
			"path" : "src/tactic/fd_solver/CMakeFiles/fd_solver.dir/./pb2bv_solver.cpp.obj"
		}
	],
	"backtrace" : 2,
	"backtraceGraph" : 
	{
		"commands" : 
		[
			"add_library",
			"z3_add_component",
			"add_dependencies",
			"z3_add_component_dependencies_to_target",
			"target_compile_options",
			"target_compile_definitions",
			"INCLUDE_DIRECTORIES",
			"target_include_directories"
		],
		"files" : 
		[
			"cmake/z3_add_component.cmake",
			"src/tactic/fd_solver/CMakeLists.txt",
			"CMakeLists.txt"
		],
		"nodes" : 
		[
			{
				"file" : 1
			},
			{
				"command" : 1,
				"file" : 1,
				"line" : 1,
				"parent" : 0
			},
			{
				"command" : 0,
				"file" : 0,
				"line" : 199,
				"parent" : 1
			},
			{
				"command" : 3,
				"file" : 0,
				"line" : 231,
				"parent" : 1
			},
			{
				"command" : 2,
				"file" : 0,
				"line" : 42,
				"parent" : 3
			},
			{
				"command" : 2,
				"file" : 0,
				"line" : 42,
				"parent" : 3
			},
			{
				"command" : 2,
				"file" : 0,
				"line" : 42,
				"parent" : 3
			},
			{
				"command" : 2,
				"file" : 0,
				"line" : 42,
				"parent" : 3
			},
			{
				"command" : 2,
				"file" : 0,
				"line" : 42,
				"parent" : 3
			},
			{
				"command" : 2,
				"file" : 0,
				"line" : 42,
				"parent" : 3
			},
			{
				"command" : 2,
				"file" : 0,
				"line" : 42,
				"parent" : 3
			},
			{
				"command" : 2,
				"file" : 0,
				"line" : 42,
				"parent" : 3
			},
			{
				"command" : 2,
				"file" : 0,
				"line" : 42,
				"parent" : 3
			},
			{
				"command" : 2,
				"file" : 0,
				"line" : 42,
				"parent" : 3
			},
			{
				"command" : 2,
				"file" : 0,
				"line" : 42,
				"parent" : 3
			},
			{
				"command" : 2,
				"file" : 0,
				"line" : 42,
				"parent" : 3
			},
			{
				"command" : 2,
				"file" : 0,
				"line" : 42,
				"parent" : 3
			},
			{
				"command" : 2,
				"file" : 0,
				"line" : 42,
				"parent" : 3
			},
			{
				"command" : 2,
				"file" : 0,
				"line" : 42,
				"parent" : 3
			},
			{
				"command" : 2,
				"file" : 0,
				"line" : 42,
				"parent" : 3
			},
			{
				"command" : 2,
				"file" : 0,
				"line" : 42,
				"parent" : 3
			},
			{
				"command" : 4,
				"file" : 0,
				"line" : 207,
				"parent" : 1
			},
			{
				"command" : 4,
				"file" : 0,
				"line" : 207,
				"parent" : 1
			},
			{
				"command" : 4,
				"file" : 0,
				"line" : 207,
				"parent" : 1
			},
			{
				"command" : 4,
				"file" : 0,
				"line" : 207,
				"parent" : 1
			},
			{
				"command" : 4,
				"file" : 0,
				"line" : 207,
				"parent" : 1
			},
			{
				"command" : 5,
				"file" : 0,
				"line" : 203,
				"parent" : 1
			},
			{
				"command" : 5,
				"file" : 0,
				"line" : 203,
				"parent" : 1
			},
			{
				"command" : 5,
				"file" : 0,
				"line" : 203,
				"parent" : 1
			},
			{
				"command" : 5,
				"file" : 0,
				"line" : 203,
				"parent" : 1
			},
			{
				"command" : 5,
				"file" : 0,
				"line" : 203,
				"parent" : 1
			},
			{
				"command" : 5,
				"file" : 0,
				"line" : 203,
				"parent" : 1
			},
			{
				"command" : 5,
				"file" : 0,
				"line" : 203,
				"parent" : 1
			},
			{
				"command" : 5,
				"file" : 0,
				"line" : 203,
				"parent" : 1
			},
			{
				"file" : 2
			},
			{
				"command" : 6,
				"file" : 2,
				"line" : 155,
				"parent" : 34
			},
			{
				"command" : 7,
				"file" : 0,
				"line" : 237,
				"parent" : 1
			},
			{
				"command" : 7,
				"file" : 0,
				"line" : 237,
				"parent" : 1
			}
		]
	},
	"compileGroups" : 
	[
		{
			"compileCommandFragments" : 
			[
				{
					"fragment" : "/DWIN32 /D_WINDOWS  /GR /EHsc /MDd /Zi /Ob0 /Od /RTC1  "
				},
				{
					"backtrace" : 21,
					"fragment" : "-openmp"
				},
				{
					"backtrace" : 22,
					"fragment" : "/fp:precise"
				},
				{
					"backtrace" : 23,
					"fragment" : "/W3"
				},
				{
					"backtrace" : 24,
					"fragment" : "/Oy-"
				},
				{
					"backtrace" : 25,
					"fragment" : "/Gd"
				}
			],
			"defines" : 
			[
				{
					"backtrace" : 26,
					"define" : "LEAN_DEBUG"
				},
				{
					"backtrace" : 27,
					"define" : "UNICODE"
				},
				{
					"backtrace" : 28,
					"define" : "Z3DEBUG"
				},
				{
					"backtrace" : 29,
					"define" : "_AMD64_"
				},
				{
					"backtrace" : 30,
					"define" : "_MP_INTERNAL"
				},
				{
					"backtrace" : 31,
					"define" : "_TRACE"
				},
				{
					"backtrace" : 32,
					"define" : "_UNICODE"
				},
				{
					"backtrace" : 33,
					"define" : "_WINDOWS"
				}
			],
			"includes" : 
			[
				{
					"backtrace" : 35,
					"path" : "/usr/local/include"
				},
				{
					"backtrace" : 36,
					"path" : "C:/Users/bottl/source/repos/z3/out/build/x64-Debug/src"
				},
				{
					"backtrace" : 37,
					"path" : "C:/Users/bottl/source/repos/z3/src"
				}
			],
			"language" : "CXX",
			"sourceIndexes" : 
			[
				0,
				1,
				2,
				3
			]
		}
	],
	"dependencies" : 
	[
		{
			"backtrace" : 4,
			"id" : "polynomial::@8d06ad2c9aca8e8772e2"
		},
		{
			"backtrace" : 5,
			"id" : "util::@6bc12a100e338ba65b7b"
		},
		{
			"backtrace" : 6,
			"id" : "sat::@d47bc915974f3a76f563"
		},
		{
			"backtrace" : 7,
			"id" : "automata::@c03fdd289820959a05fe"
		},
		{
			"backtrace" : 8,
			"id" : "tactic::@2f580a174d3ebf960039"
		},
		{
			"backtrace" : 9,
			"id" : "model::@dd52281f56f5d51f359a"
		},
		{
			"backtrace" : 10,
			"id" : "ast::@82451c30a77be7f89338"
		},
		{
			"backtrace" : 11,
			"id" : "normal_forms::@01848afe0d99e15ba6cb"
		},
		{
			"backtrace" : 12,
			"id" : "rewriter::@edda3ad5ea2f8f14cc34"
		},
		{
			"backtrace" : 13,
			"id" : "core_tactics::@885f93e0c2973fa4378b"
		},
		{
			"backtrace" : 14,
			"id" : "sat_tactic::@031b9ebd0e99b81a54d9"
		},
		{
			"backtrace" : 15,
			"id" : "aig_tactic::@95cb9968617a17bbdb77"
		},
		{
			"backtrace" : 16,
			"id" : "solver::@56b03cb272704949ecff"
		},
		{
			"backtrace" : 17,
			"id" : "arith_tactics::@19e8c294bfdda7d34b92"
		},
		{
			"backtrace" : 18,
			"id" : "bit_blaster::@4831973c81ed785dd86f"
		},
		{
			"backtrace" : 19,
			"id" : "bv_tactics::@f293013ec1d162b008e2"
		},
		{
			"backtrace" : 20,
			"id" : "sat_solver::@2680c2e3d82a770fd23d"
		}
	],
	"id" : "fd_solver::@a712938b521207bb84bf",
	"name" : "fd_solver",
	"paths" : 
	{
		"build" : "src/tactic/fd_solver",
		"source" : "src/tactic/fd_solver"
	},
	"sourceGroups" : 
	[
		{
			"name" : "Source Files",
			"sourceIndexes" : 
			[
				0,
				1,
				2,
				3
			]
		}
	],
	"sources" : 
	[
		{
			"backtrace" : 2,
			"compileGroupIndex" : 0,
			"path" : "src/tactic/fd_solver/bounded_int2bv_solver.cpp",
			"sourceGroupIndex" : 0
		},
		{
			"backtrace" : 2,
			"compileGroupIndex" : 0,
			"path" : "src/tactic/fd_solver/enum2bv_solver.cpp",
			"sourceGroupIndex" : 0
		},
		{
			"backtrace" : 2,
			"compileGroupIndex" : 0,
			"path" : "src/tactic/fd_solver/fd_solver.cpp",
			"sourceGroupIndex" : 0
		},
		{
			"backtrace" : 2,
			"compileGroupIndex" : 0,
			"path" : "src/tactic/fd_solver/pb2bv_solver.cpp",
			"sourceGroupIndex" : 0
		}
	],
	"type" : "OBJECT_LIBRARY"
}
